thehunter_rwn/.env
thehunter_rwn/__init__.py
thehunter_rwn/active_scan.py
thehunter_rwn/exploit.py
thehunter_rwn/main.py
thehunter_rwn/passive_scan.py
thehunter_rwn-0.1.1.dist-info/entry_points.txt
thehunter_rwn-0.1.1.dist-info/METADATA
thehunter_rwn-0.1.1.dist-info/WHEEL
thehunter_rwn-0.1.1.dist-info/RECORD
