Metadata-Version: 2.1
Name: thehunter-rwn
Version: 0.1.1
Summary: 
Author: Rawan
Author-email: rwnalhabsi98@gmail.com
Requires-Python: >=3.13,<4.0
Classifier: Programming Language :: Python :: 3
Classifier: Programming Language :: Python :: 3.13
Requires-Dist: python-dotenv (>=1.0.1,<2.0.0)
Requires-Dist: requests (>=2.32.3,<3.0.0)
Requires-Dist: rich (>=13.9.4,<14.0.0)
Requires-Dist: typer (>=0.15.1,<0.16.0)
